deepmodeling_sphinx/__init__.py
deepmodeling_sphinx/authors.py
deepmodeling_sphinx/banner.css
deepmodeling_sphinx/banner.html
deepmodeling_sphinx/banner.js
deepmodeling_sphinx/config.py
deepmodeling_sphinx/dark_rtd.css
deepmodeling_sphinx/inject.py
deepmodeling_sphinx-0.3.2.dist-info/licenses/LICENSE
deepmodeling_sphinx-0.3.2.dist-info/METADATA
deepmodeling_sphinx-0.3.2.dist-info/WHEEL
deepmodeling_sphinx-0.3.2.dist-info/top_level.txt
deepmodeling_sphinx-0.3.2.dist-info/RECORD
