Metadata-Version: 2.4
Name: deepmodeling_sphinx
Version: 0.3.2
Summary: Sphinx extension for DeepModeling projects.
Author: DeepModeling
License:                    GNU LESSER GENERAL PUBLIC LICENSE
Project-URL: Homepage, https://github.com/deepmodeling/deepmodeling_sphinx
Project-URL: documentation, https://docs.deepmodeling.com/projects/deepmodeling-sphinx/
Project-URL: repository, https://github.com/deepmodeling/deepmodeling_sphinx
Classifier: Programming Language :: Python
Classifier: Programming Language :: Python :: 3
Requires-Python: >=3.7
License-File: LICENSE
Requires-Dist: sphinx
Requires-Dist: minify-html!=0.16.*,!=0.17.0
Requires-Dist: jsmin
Requires-Dist: cssmin
Requires-Dist: jinja2
Dynamic: license-file
